sctrain/__init__.py
sctrain/co_training.py
sctrain/data.py
sctrain/k_fold.py
sctrain/models.py
sctrain/results.py
sctrain/self_training.py
simple_co_train-1.0.0.dist-info/AUTHORS.rst
simple_co_train-1.0.0.dist-info/LICENSE
simple_co_train-1.0.0.dist-info/METADATA
simple_co_train-1.0.0.dist-info/WHEEL
simple_co_train-1.0.0.dist-info/top_level.txt
simple_co_train-1.0.0.dist-info/RECORD
