Metadata-Version: 2.1
Name: simple-co-train
Version: 1.0.0
Summary: A simple co-training library built on Keras.
Home-page: UNKNOWN
Author: Daniel Marinov Petrov
Author-email: daniel.marinov.a100111@mcast.edu.mt
License: MIT
Platform: UNKNOWN
Classifier: Development Status :: 5 - Production/Stable
Classifier: Intended Audience :: Developers
Classifier: License :: OSI Approved :: MIT License
Classifier: Operating System :: Unix
Classifier: Operating System :: POSIX
Classifier: Operating System :: Microsoft :: Windows
Classifier: Programming Language :: Python
Classifier: Programming Language :: Python :: 3.5
Classifier: Programming Language :: Python :: 3.6
Classifier: Programming Language :: Python :: 3.7
Classifier: Programming Language :: Python :: Implementation :: CPython
Classifier: Programming Language :: Python :: Implementation :: PyPy
Classifier: Topic :: Utilities
Requires-Python: >=2.7, !=3.0.*, !=3.1.*, !=3.2.*, !=3.3.*, !=3.4.*
Requires-Dist: keras
Requires-Dist: pandas
Requires-Dist: numpy
Requires-Dist: scikit-learn
